[
 {
  "url": [],
  "atime": 1541475882,
  "ncos": 2,
  "thumb": "http://img6.dl.ltimg.net/5be10e2ae7bce76459a43b25?auth_key=1543548678-5c00a7fec8cfb72caaf7d5e8-0-3fde5982f06da9626f13275c8c65a881&imageMogr2/thumbnail/!750x750r/gravity/Center/crop/750x750",
  "rank": 9,
  "name": "",
  "tag": [
   "猫头鹰",
   "歪头杀",
   "疑问",
   "可爱",
   "大眼睛"
  ],
  "view": 0,
  "cr": [],
  "favs": 0,
  "id": "5be10e2ae7bce76459a43b25",
  "desc": ""
 },
 {
  "url": [],
  "atime": 1514286808,
  "ncos": 27,
  "thumb": "http://img6.dl.ltimg.net/5a422ed8e7bce72567568b5f?auth_key=1543548955-5c00a913c8cfb72cd7781a77-0-bf48da5686abc5bc9e85e069c3d46bd8&imageMogr2/thumbnail/!750x750r/gravity/Center/crop/750x750",
  "rank": 126,
  "name": "",
  "tag": [
   "卡通",
   "可爱",
   "个性"
  ],
  "view": 0,
  "cr": [],
  "favs": 0,
  "id": "5a422ed8e7bce72567568b5f",
  "desc": ""
 },
 {
  "url": [],
  "atime": 1536034872,
  "ncos": 1,
  "thumb": "http://img6.dl.ltimg.net/5b8e0838e7bce763fd022236?auth_key=1543548875-5c00a8c3c8cfb72cd778195c-0-48f207e1ba54ed8a16fd1257f856055d&imageMogr2/thumbnail/!750x750r/gravity/Center/crop/750x750",
  "rank": 22,
  "name": "",
  "tag": [
   "唐老鸭",
   "搞怪",
   "鸭鸭",
   "卡通",
   "可爱",
   "个性"
  ],
  "view": 0,
  "cr": [],
  "favs": 0,
  "id": "5b8e0838e7bce763fd022236",
  "desc": ""
 },
 {
  "url": [],
  "atime": 1542082780,
  "ncos": 1,
  "thumb": "http://img6.dl.ltimg.net/5bea50dce7bce7648e615faa?auth_key=1543548678-5c00a7fec8cfb72caaf7d5e5-0-7d5945c663b79bcabfd164818c3828ab&imageMogr2/thumbnail/!750x750r/gravity/Center/crop/750x750",
  "rank": 11,
  "name": "",
  "tag": [
   "青蛙",
   "表情包",
   "可爱",
   "腿长"
  ],
  "view": 0,
  "cr": [],
  "favs": 0,
  "id": "5bea50dce7bce7648e615faa",
  "desc": ""
 },
 {
  "url": [],
  "atime": 1533031234,
  "ncos": 5,
  "thumb": "http://img6.dl.ltimg.net/5b603342e7bce7670c241cc6?auth_key=1543549803-5c00ac63c8cfb72caaf7efe7-0-78391fc12f9efdbbd5d3ef6164784296&imageMogr2/thumbnail/!750x750r/gravity/Center/crop/750x750",
  "rank": 19,
  "name": "",
  "tag": [
   "哆啦A梦",
   "有趣",
   "搞笑",
   "可爱",
   "个性",
   "头像"
  ],
  "view": 0,
  "cr": [],
  "favs": 0,
  "id": "5b603342e7bce7670c241cc6",
  "desc": ""
 },
 {
  "url": [],
  "atime": 1537260824,
  "ncos": 3,
  "thumb": "http://img6.dl.ltimg.net/5ba0bd18e7bce763fd022b7a?auth_key=1543548875-5c00a8c3c8cfb72cd7781949-0-bfce9a9a09c12ec4c408d38f9a819a98&imageMogr2/thumbnail/!750x750r/gravity/Center/crop/750x750",
  "rank": 34,
  "name": "",
  "tag": [
   "搞怪",
   "个性",
   "有趣",
   "搞笑"
  ],
  "view": 0,
  "cr": [],
  "favs": 0,
  "id": "5ba0bd18e7bce763fd022b7a",
  "desc": ""
 },
 {
  "url": [],
  "atime": 1518336178,
  "ncos": 7,
  "thumb": "http://img6.dl.ltimg.net/5a7ff8b2e7bce7259115e662?auth_key=1543550763-5c00b023c8cfb72caaf81606-0-5232b6dc8691b0657b4a6e7e69f9f51f&imageMogr2/thumbnail/!750x750r/gravity/Center/crop/750x750",
  "rank": 44,
  "name": "",
  "tag": [
   "新年",
   "红色",
   "个性"
  ],
  "view": 0,
  "cr": [],
  "favs": 0,
  "id": "5a7ff8b2e7bce7259115e662",
  "desc": ""
 },
 {
  "url": [],
  "atime": 1521449864,
  "ncos": 2,
  "thumb": "http://img6.dl.ltimg.net/5aaf7b88e7bce7257c730e2a?auth_key=1543550763-5c00b023c8cfb72caaf815f8-0-f5f535a645058514bf5b35638bf591a0&imageMogr2/thumbnail/!750x750r/gravity/Center/crop/750x750",
  "rank": 33,
  "name": "",
  "tag": [
   "小孩子",
   "个性",
   "可爱"
  ],
  "view": 0,
  "cr": [],
  "favs": 0,
  "id": "5aaf7b88e7bce7257c730e2a",
  "desc": ""
 },
 {
  "url": [],
  "atime": 1514286788,
  "ncos": 2,
  "thumb": "http://img6.dl.ltimg.net/5a422ec4e7bce7253c78b2b8?auth_key=1543548955-5c00a913c8cfb72cd7781a78-0-ef7470ac2138f972848ce32927d64d35&imageMogr2/thumbnail/!750x750r/gravity/Center/crop/750x750",
  "rank": 27,
  "name": "",
  "tag": [
   "个性",
   "动漫",
   "卡通"
  ],
  "view": 0,
  "cr": [],
  "favs": 0,
  "id": "5a422ec4e7bce7253c78b2b8",
  "desc": ""
 },
 {
  "url": [],
  "atime": 1505815734,
  "ncos": 3,
  "thumb": "http://img6.dl.ltimg.net/59c0ecb5e7bce729eca94d09?auth_key=1543549603-5c00ab9bc8cfb72cbcf42b9d-0-2db62e392d504d48b827d621ae18bd48&imageMogr2/thumbnail/!750x750r/gravity/Center/crop/750x750",
  "rank": 23,
  "name": "",
  "tag": [
   "黑白",
   "简洁",
   "可爱",
   "个性"
  ],
  "view": 0,
  "cr": [],
  "favs": 0,
  "id": "59c0ecb5e7bce729eca94d09",
  "desc": ""
 },
 {
  "url": [],
  "atime": 1506687476,
  "ncos": 1,
  "thumb": "http://img6.dl.ltimg.net/59ce39f4e7bce729500bc27a?auth_key=1543549603-5c00ab9bc8cfb72cbcf42b91-0-5c4dc69e712561269bd81dc83499c708&imageMogr2/thumbnail/!750x750r/gravity/Center/crop/750x750",
  "rank": 27,
  "name": "",
  "tag": [
   "文字",
   "个性",
   "简洁"
  ],
  "view": 0,
  "cr": [],
  "favs": 0,
  "id": "59ce39f4e7bce729500bc27a",
  "desc": ""
 },
 {
  "url": [],
  "atime": 1524541033,
  "ncos": 6,
  "thumb": "http://img6.dl.ltimg.net/5adea669e7bce72552e6a2fa?auth_key=1543549544-5c00ab60c8cfb72cd77836b8-0-61a978df22f3cfa349a9c345ebef2c48&imageMogr2/thumbnail/!750x750r/gravity/Center/crop/750x750",
  "rank": 41,
  "name": "",
  "tag": [
   "外卖头像",
   "蘑菇头",
   "时尚",
   "搞笑",
   "有趣"
  ],
  "view": 0,
  "cr": [],
  "favs": 0,
  "id": "5adea669e7bce72552e6a2fa",
  "desc": ""
 },
 {
  "url": [],
  "atime": 1519290252,
  "ncos": 2,
  "thumb": "http://img6.dl.ltimg.net/5a8e878ce7bce7259115e853?auth_key=1543550763-5c00b023c8cfb72caaf81605-0-e57dc125c6cddb08629a2215ab680091&imageMogr2/thumbnail/!750x750r/gravity/Center/crop/750x750",
  "rank": 18,
  "name": "",
  "tag": [
   "文字",
   "个性",
   "黑白"
  ],
  "view": 0,
  "cr": [],
  "favs": 0,
  "id": "5a8e878ce7bce7259115e853",
  "desc": ""
 },
 {
  "url": [],
  "atime": 1526356913,
  "ncos": 1,
  "thumb": "http://img6.dl.ltimg.net/5afa5bb1e7bce72552e6aab9?auth_key=1543549544-5c00ab60c8cfb72cd77836b3-0-8e4ca7dec736c5b549f49f8f09991774&imageMogr2/thumbnail/!750x750r/gravity/Center/crop/750x750",
  "rank": 8,
  "name": "",
  "tag": [
   "文字",
   "个性",
   "搞笑",
   "简约"
  ],
  "view": 0,
  "cr": [],
  "favs": 0,
  "id": "5afa5bb1e7bce72552e6aab9",
  "desc": ""
 },
 {
  "url": [],
  "atime": 1538034117,
  "ncos": 0,
  "thumb": "http://img6.dl.ltimg.net/5bac89c5e7bce763fd023196?auth_key=1543548678-5c00a7fec8cfb72caaf7d5f6-0-3d643e60799009d0325df4e15cb1c44b&imageMogr2/thumbnail/!750x750r/gravity/Center/crop/750x750",
  "rank": 12,
  "name": "",
  "tag": [
   "搞怪",
   "个性",
   "搞笑",
   "创意",
   "有趣"
  ],
  "view": 0,
  "cr": [],
  "favs": 0,
  "id": "5bac89c5e7bce763fd023196",
  "desc": ""
 },
 {
  "url": [],
  "atime": 1513676894,
  "ncos": 3,
  "thumb": "http://img6.dl.ltimg.net/5a38e05ee7bce7251e7c358b?auth_key=1543548955-5c00a913c8cfb72cd7781a82-0-ad780ffd3899747a9c886cfaea3c08a0&imageMogr2/thumbnail/!750x750r/gravity/Center/crop/750x750",
  "rank": 42,
  "name": "",
  "tag": [
   "黑白",
   "剪刀手",
   "个性"
  ],
  "view": 0,
  "cr": [],
  "favs": 0,
  "id": "5a38e05ee7bce7251e7c358b",
  "desc": ""
 },
 {
  "url": [],
  "atime": 1519290252,
  "ncos": 5,
  "thumb": "http://img6.dl.ltimg.net/5a8e878ce7bce7259115e856?auth_key=1543550763-5c00b023c8cfb72caaf81602-0-38ba7e3c0e8d6cc96e714cec656634a6&imageMogr2/thumbnail/!750x750r/gravity/Center/crop/750x750",
  "rank": 41,
  "name": "",
  "tag": [
   "文字",
   "个性",
   "黑白"
  ],
  "view": 0,
  "cr": [],
  "favs": 0,
  "id": "5a8e878ce7bce7259115e856",
  "desc": ""
 },
 {
  "url": [],
  "atime": 1523932584,
  "ncos": 2,
  "thumb": "http://img6.dl.ltimg.net/5ad55da8e7bce7257c731a80?auth_key=1543549544-5c00ab60c8cfb72cd77836c1-0-99c4c3c0c2cafe7fb24768b110460602&imageMogr2/thumbnail/!750x750r/gravity/Center/crop/750x750",
  "rank": 15,
  "name": "",
  "tag": [
   "萌宠",
   "可爱",
   "搞怪",
   "创意",
   "有趣"
  ],
  "view": 0,
  "cr": [],
  "favs": 0,
  "id": "5ad55da8e7bce7257c731a80",
  "desc": ""
 },
 {
  "url": [],
  "atime": 1511440757,
  "ncos": 1,
  "thumb": "http://img6.dl.ltimg.net/5a16c175e7bce7257c72f516?auth_key=1543548964-5c00a91cc8cfb72cd7781ad3-0-2949ec219961b012e10f15fb278f0b1d&imageMogr2/thumbnail/!750x750r/gravity/Center/crop/750x750",
  "rank": 13,
  "name": "",
  "tag": [
   "女生",
   "可爱",
   "小女孩"
  ],
  "view": 0,
  "cr": [],
  "favs": 0,
  "id": "5a16c175e7bce7257c72f516",
  "desc": ""
 },
 {
  "url": [],
  "atime": 1536030344,
  "ncos": 1,
  "thumb": "http://img6.dl.ltimg.net/5b8df688e7bce7642568438e?auth_key=1543549788-5c00ac54c8cfb72caaf7ef66-0-97fd5dcb60cf2da6ccf2d334672ba922&imageMogr2/thumbnail/!750x750r/gravity/Center/crop/750x750",
  "rank": 28,
  "name": "",
  "tag": [
   "搞怪",
   "有趣",
   "小人",
   "简笔画",
   "个性"
  ],
  "view": 0,
  "cr": [],
  "favs": 0,
  "id": "5b8df688e7bce7642568438e",
  "desc": ""
 },
 {
  "url": [],
  "atime": 1504610334,
  "ncos": 3,
  "thumb": "http://img6.dl.ltimg.net/59ae881ee7bce72994d8fae2?auth_key=1543549603-5c00ab9bc8cfb72cbcf42ba2-0-a031cc3b798636e6e3c849f03c49f6ce&imageMogr2/thumbnail/!750x750r/gravity/Center/crop/750x750",
  "rank": 18,
  "name": "",
  "tag": [
   "个性",
   "文字",
   "搞笑"
  ],
  "view": 0,
  "cr": [],
  "favs": 0,
  "id": "59ae881ee7bce72994d8fae2",
  "desc": ""
 },
 {
  "url": [],
  "atime": 1503479134,
  "ncos": 3,
  "thumb": "http://img6.dl.ltimg.net/599d455de7bce72994d8f6a6?auth_key=1543550169-5c00add1c8cfb72ca6310df5-0-7c066f345ddba913bb44fbe8e6597039&imageMogr2/thumbnail/!750x750r/gravity/Center/crop/750x750",
  "rank": 27,
  "name": "",
  "tag": [
   "可爱",
   "个性",
   "搞笑"
  ],
  "view": 0,
  "cr": [],
  "favs": 0,
  "id": "599d455de7bce72994d8f6a6",
  "desc": ""
 },
 {
  "url": [],
  "atime": 1535601596,
  "ncos": 1,
  "thumb": "http://img6.dl.ltimg.net/5b876bbbe7bce7375fd57103?auth_key=1543549788-5c00ac54c8cfb72caaf7ef6f-0-ff58c26eb6216ccebf8a3f105e951889&imageMogr2/thumbnail/!750x750r/gravity/Center/crop/750x750",
  "rank": 3,
  "name": "",
  "tag": [
   "鸭鸭",
   "可爱",
   "害羞",
   "搞怪",
   "个性"
  ],
  "view": 0,
  "cr": [],
  "favs": 0,
  "id": "5b876bbbe7bce7375fd57103",
  "desc": ""
 },
 {
  "url": [],
  "atime": 1537424936,
  "ncos": 4,
  "thumb": "http://img6.dl.ltimg.net/5ba33e27e7bce76425684dc4?auth_key=1543548875-5c00a8c3c8cfb72cd7781940-0-097a0260339f3eff63431426259dd6b1&imageMogr2/thumbnail/!750x750r/gravity/Center/crop/750x750",
  "rank": 30,
  "name": "",
  "tag": [
   "黑白",
   "简笔画",
   "简单",
   "插画",
   "情头"
  ],
  "view": 0,
  "cr": [],
  "favs": 0,
  "id": "5ba33e27e7bce76425684dc4",
  "desc": ""
 },
 {
  "url": [],
  "atime": 1536560666,
  "ncos": 1,
  "thumb": "http://img6.dl.ltimg.net/5b960e1ae7bce763734076e2?auth_key=1543548875-5c00a8c3c8cfb72cd7781951-0-252d0ef21f9ac5adb02bb6a473564715&imageMogr2/thumbnail/!750x750r/gravity/Center/crop/750x750",
  "rank": 20,
  "name": "",
  "tag": [
   "科米蛙",
   "可爱",
   "抽烟",
   "有趣",
   "个性"
  ],
  "view": 0,
  "cr": [],
  "favs": 0,
  "id": "5b960e1ae7bce763734076e2",
  "desc": ""
 },
 {
  "url": [],
  "atime": 1511440846,
  "ncos": 3,
  "thumb": "http://img6.dl.ltimg.net/5a16c1cee7bce7259115d526?auth_key=1543548964-5c00a91cc8cfb72cd7781ace-0-f52323798d6a890aa447db7b11fe356c&imageMogr2/thumbnail/!750x750r/gravity/Center/crop/750x750",
  "rank": 9,
  "name": "",
  "tag": [
   "风景",
   "窗户",
   "个性"
  ],
  "view": 0,
  "cr": [],
  "favs": 0,
  "id": "5a16c1cee7bce7259115d526",
  "desc": ""
 },
 {
  "url": [],
  "atime": 1537260824,
  "ncos": 9,
  "thumb": "http://img6.dl.ltimg.net/5ba0bd18e7bce763fd022b79?auth_key=1543548875-5c00a8c3c8cfb72cd778194a-0-361fd8f421381d49e8fdfa9a4ff4aa16&imageMogr2/thumbnail/!750x750r/gravity/Center/crop/750x750",
  "rank": 44,
  "name": "",
  "tag": [
   "搞怪",
   "个性",
   "有趣",
   "搞笑"
  ],
  "view": 0,
  "cr": [],
  "favs": 0,
  "id": "5ba0bd18e7bce763fd022b79",
  "desc": ""
 },
 {
  "url": [],
  "atime": 1536030344,
  "ncos": 0,
  "thumb": "http://img6.dl.ltimg.net/5b8df688e7bce7642568438a?auth_key=1543549788-5c00ac54c8cfb72caaf7ef6a-0-8363bfbe19e147b1a370e9023ec0a227&imageMogr2/thumbnail/!750x750r/gravity/Center/crop/750x750",
  "rank": 8,
  "name": "",
  "tag": [
   "搞怪",
   "有趣",
   "小人",
   "简笔画",
   "个性"
  ],
  "view": 0,
  "cr": [],
  "favs": 0,
  "id": "5b8df688e7bce7642568438a",
  "desc": ""
 },
 {
  "url": [],
  "atime": 1511441076,
  "ncos": 5,
  "thumb": "http://img6.dl.ltimg.net/5a16c2b3e7bce7259115d528?auth_key=1543548955-5c00a913c8cfb72cd7781a91-0-5561031db65343c7f4fd7458972c548f&imageMogr2/thumbnail/!750x750r/gravity/Center/crop/750x750",
  "rank": 15,
  "name": "",
  "tag": [
   "截图",
   "个性",
   "欧美"
  ],
  "view": 0,
  "cr": [],
  "favs": 0,
  "id": "5a16c2b3e7bce7259115d528",
  "desc": ""
 },
 {
  "url": [],
  "atime": 1534231988,
  "ncos": 3,
  "thumb": "http://img6.dl.ltimg.net/5b7285b4e7bce7667a68db61?auth_key=1543549803-5c00ac63c8cfb72caaf7efe5-0-b1b4fbb6f32b021cdcad35005c23fa4a&imageMogr2/thumbnail/!750x750r/gravity/Center/crop/750x750",
  "rank": 19,
  "name": "",
  "tag": [
   "搞怪",
   "有趣",
   "搞笑",
   "个性"
  ],
  "view": 0,
  "cr": [],
  "favs": 0,
  "id": "5b7285b4e7bce7667a68db61",
  "desc": ""
 }
]